pytest_fxa/__init__.py
pytest_fxa/plugin.py
pytest_fxa-1.4.0.dist-info/METADATA
pytest_fxa-1.4.0.dist-info/RECORD
pytest_fxa-1.4.0.dist-info/WHEEL
pytest_fxa-1.4.0.dist-info/entry_points.txt
pytest_fxa-1.4.0.dist-info/top_level.txt
